pycubing/__init__.py
pycubing/cube.py
pycubing/enums.py
pycubing/error.py
pycubing/scrambles.json
pycubing/utils.py
pycubing/cv/__init__.py
pycubing/solver/__init__.py
pycubing/solver/__main__.py
pycubing/solver/solver2x2.py
pycubing/solver/solver3x3.py
pycubing/solver/solverNxN.py
pycubing-0.1.5.dist-info/LICENSE
pycubing-0.1.5.dist-info/METADATA
pycubing-0.1.5.dist-info/WHEEL
pycubing-0.1.5.dist-info/top_level.txt
pycubing-0.1.5.dist-info/RECORD
